{
  "timeZone": {
    "id": "Africa/Johannesburg",
    "version": ""
  },
  "weatherCondition": {
    "iconBaseUri": "https://maps.gstatic.com/weather/v1/drizzle",
    "description": {
      "text": "Light rain",
      "languageCode": "en"
    },
    "type": "LIGHT_RAIN"
  },
  "temperature": {
    "unit": "CELSIUS",
    "degrees": 14
  },
  "feelsLikeTemperature": {
    "unit": "CELSIUS",
    "degrees": 12
  },
  "dewPoint": {
    "unit": "CELSIUS",
    "degrees": 10.8
  },
  "heatIndex": {
    "unit": "CELSIUS",
    "degrees": 14
  },
  "windChill": {
    "unit": "CELSIUS",
    "degrees": 12
  },
  "precipitation": {
    "probability": {
      "type": "LIGHT_RAIN",
      "percent": 55
    },
    "snowQpf": {
      "unit": "MILLIMETERS",
      "quantity": 0
    },
    "qpf": {
      "unit": "MILLIMETERS",
      "quantity": 0.96
    }
  },
  "airPressure": {
    "meanSeaLevelMillibars": 1026.51
  },
  "wind": {
    "direction": {
      "cardinal": "SOUTHWEST",
      "degrees": 224
    },
    "speed": {
      "unit": "KILOMETERS_PER_HOUR",
      "value": 26
    },
    "gust": {
      "unit": "KILOMETERS_PER_HOUR",
      "value": 31
    }
  },
  "visibility": {
    "unit": "KILOMETERS",
    "distance": 16
  },
  "currentConditionsHistory": {
    "temperatureChange": {
      "unit": "CELSIUS",
      "degrees": -1.4
    },
    "maxTemperature": {
      "unit": "CELSIUS",
      "degrees": 19.8
    },
    "minTemperature": {
      "unit": "CELSIUS",
      "degrees": 13
    },
    "snowQpf": {
      "unit": "MILLIMETERS",
      "quantity": 0
    },
    "qpf": {
      "unit": "MILLIMETERS",
      "quantity": 4.44
    }
  },
  "currentTime": "2026-07-23T20:56:22.307724163Z",
  "isDaytime": false,
  "relativeHumidity": 80,
  "uvIndex": 0,
  "thunderstormProbability": 11,
  "cloudCover": 73
}