{
  "currentTime": "2025-06-25T07:16:18.975035789Z",
  "timeZone": {
    "id": "Africa/Johannesburg"
  },
  "isDaytime": true,
  "weatherCondition": {
    "iconBaseUri": "https://maps.gstatic.com/weather/v1/party_cloudy",
    "description": {
      "text": "Partly sunny",
      "languageCode": "en"
    },
    "type": "PARTLY_CLOUDY"
  },
  "temperature": {
    "degrees": 18.2,
    "unit": "CELSIUS"
  },
  "feelsLikeTemperature": {
    "degrees": 18.9,
    "unit": "CELSIUS"
  },
  "dewPoint": {
    "degrees": 5.9,
    "unit": "CELSIUS"
  },
  "heatIndex": {
    "degrees": 19.2,
    "unit": "CELSIUS"
  },
  "windChill": {
    "degrees": 17.9,
    "unit": "CELSIUS"
  },
  "relativeHumidity": 46,
  "uvIndex": 1,
  "precipitation": {
    "probability": {
      "percent": 1,
      "type": "RAIN"
    },
    "snowQpf": {
      "quantity": 0,
      "unit": "MILLIMETERS"
    },
    "qpf": {
      "quantity": 0,
      "unit": "MILLIMETERS"
    }
  },
  "thunderstormProbability": 0,
  "airPressure": {
    "meanSeaLevelMillibars": 1002.77
  },
  "wind": {
    "direction": {
      "degrees": 315,
      "cardinal": "NORTHWEST"
    },
    "speed": {
      "value": 13,
      "unit": "KILOMETERS_PER_HOUR"
    },
    "gust": {
      "value": 24,
      "unit": "KILOMETERS_PER_HOUR"
    }
  },
  "visibility": {
    "distance": 16,
    "unit": "KILOMETERS"
  },
  "cloudCover": 44,
  "currentConditionsHistory": {
    "temperatureChange": {
      "degrees": 5.7,
      "unit": "CELSIUS"
    },
    "maxTemperature": {
      "degrees": 20.4,
      "unit": "CELSIUS"
    },
    "minTemperature": {
      "degrees": 12.4,
      "unit": "CELSIUS"
    },
    "snowQpf": {
      "quantity": 0,
      "unit": "MILLIMETERS"
    },
    "qpf": {
      "quantity": 0,
      "unit": "MILLIMETERS"
    }
  }
}