{
  "currentTime": "2026-03-03T17:39:35.745987212Z",
  "timeZone": {
    "id": "Africa/Johannesburg"
  },
  "isDaytime": false,
  "weatherCondition": {
    "iconBaseUri": "https://maps.gstatic.com/weather/v1/clear",
    "description": {
      "text": "Clear",
      "languageCode": "en"
    },
    "type": "CLEAR"
  },
  "temperature": {
    "degrees": 18.5,
    "unit": "CELSIUS"
  },
  "feelsLikeTemperature": {
    "degrees": 20.3,
    "unit": "CELSIUS"
  },
  "dewPoint": {
    "degrees": 14.5,
    "unit": "CELSIUS"
  },
  "heatIndex": {
    "degrees": 20.4,
    "unit": "CELSIUS"
  },
  "windChill": {
    "degrees": 18.3,
    "unit": "CELSIUS"
  },
  "relativeHumidity": 77,
  "uvIndex": 0,
  "precipitation": {
    "probability": {
      "percent": 0,
      "type": "RAIN"
    },
    "snowQpf": {
      "quantity": 0,
      "unit": "MILLIMETERS"
    },
    "qpf": {
      "quantity": 0,
      "unit": "MILLIMETERS"
    }
  },
  "thunderstormProbability": 0,
  "airPressure": {
    "meanSeaLevelMillibars": 1015.01
  },
  "wind": {
    "direction": {
      "degrees": 253,
      "cardinal": "WEST_SOUTHWEST"
    },
    "speed": {
      "value": 18,
      "unit": "KILOMETERS_PER_HOUR"
    },
    "gust": {
      "value": 19,
      "unit": "KILOMETERS_PER_HOUR"
    }
  },
  "visibility": {
    "distance": 16,
    "unit": "KILOMETERS"
  },
  "cloudCover": 0,
  "currentConditionsHistory": {
    "temperatureChange": {
      "degrees": 0.2,
      "unit": "CELSIUS"
    },
    "maxTemperature": {
      "degrees": 21.7,
      "unit": "CELSIUS"
    },
    "minTemperature": {
      "degrees": 14.8,
      "unit": "CELSIUS"
    },
    "snowQpf": {
      "quantity": 0,
      "unit": "MILLIMETERS"
    },
    "qpf": {
      "quantity": 0,
      "unit": "MILLIMETERS"
    }
  }
}