{
  "currentTime": "2026-02-23T22:35:45.163846994Z",
  "timeZone": {
    "id": "Africa/Johannesburg"
  },
  "isDaytime": false,
  "weatherCondition": {
    "iconBaseUri": "https://maps.gstatic.com/weather/v1/mostly_cloudy_night",
    "description": {
      "text": "Mostly cloudy",
      "languageCode": "en"
    },
    "type": "MOSTLY_CLOUDY"
  },
  "temperature": {
    "degrees": 20,
    "unit": "CELSIUS"
  },
  "feelsLikeTemperature": {
    "degrees": 24.2,
    "unit": "CELSIUS"
  },
  "dewPoint": {
    "degrees": 17.7,
    "unit": "CELSIUS"
  },
  "heatIndex": {
    "degrees": 24.2,
    "unit": "CELSIUS"
  },
  "windChill": {
    "degrees": 20,
    "unit": "CELSIUS"
  },
  "relativeHumidity": 86,
  "uvIndex": 0,
  "precipitation": {
    "probability": {
      "percent": 8,
      "type": "RAIN"
    },
    "snowQpf": {
      "quantity": 0,
      "unit": "MILLIMETERS"
    },
    "qpf": {
      "quantity": 0.1,
      "unit": "MILLIMETERS"
    }
  },
  "thunderstormProbability": 0,
  "airPressure": {
    "meanSeaLevelMillibars": 1005.29
  },
  "wind": {
    "direction": {
      "degrees": 272,
      "cardinal": "WEST"
    },
    "speed": {
      "value": 21,
      "unit": "KILOMETERS_PER_HOUR"
    },
    "gust": {
      "value": 23,
      "unit": "KILOMETERS_PER_HOUR"
    }
  },
  "visibility": {
    "distance": 16,
    "unit": "KILOMETERS"
  },
  "cloudCover": 81,
  "currentConditionsHistory": {
    "temperatureChange": {
      "degrees": -1.8,
      "unit": "CELSIUS"
    },
    "maxTemperature": {
      "degrees": 22.5,
      "unit": "CELSIUS"
    },
    "minTemperature": {
      "degrees": 19.8,
      "unit": "CELSIUS"
    },
    "snowQpf": {
      "quantity": 0,
      "unit": "MILLIMETERS"
    },
    "qpf": {
      "quantity": 1.76,
      "unit": "MILLIMETERS"
    }
  }
}