{
  "timeZone": {
    "id": "Africa/Johannesburg",
    "version": ""
  },
  "weatherCondition": {
    "iconBaseUri": "https://maps.gstatic.com/weather/v1/partly_clear",
    "description": {
      "text": "Partly cloudy",
      "languageCode": "en"
    },
    "type": "PARTLY_CLOUDY"
  },
  "temperature": {
    "unit": "CELSIUS",
    "degrees": 13.3
  },
  "feelsLikeTemperature": {
    "unit": "CELSIUS",
    "degrees": 13.1
  },
  "dewPoint": {
    "unit": "CELSIUS",
    "degrees": 10.5
  },
  "heatIndex": {
    "unit": "CELSIUS",
    "degrees": 13.3
  },
  "windChill": {
    "unit": "CELSIUS",
    "degrees": 13.1
  },
  "precipitation": {
    "probability": {
      "type": "RAIN",
      "percent": 4
    },
    "snowQpf": {
      "unit": "MILLIMETERS",
      "quantity": 0
    },
    "qpf": {
      "unit": "MILLIMETERS",
      "quantity": 0
    }
  },
  "airPressure": {
    "meanSeaLevelMillibars": 1019.77
  },
  "wind": {
    "direction": {
      "cardinal": "NORTHEAST",
      "degrees": 49
    },
    "speed": {
      "unit": "KILOMETERS_PER_HOUR",
      "value": 6
    },
    "gust": {
      "unit": "KILOMETERS_PER_HOUR",
      "value": 13
    }
  },
  "visibility": {
    "unit": "KILOMETERS",
    "distance": 16
  },
  "currentConditionsHistory": {
    "temperatureChange": {
      "unit": "CELSIUS",
      "degrees": 0.9
    },
    "maxTemperature": {
      "unit": "CELSIUS",
      "degrees": 17
    },
    "minTemperature": {
      "unit": "CELSIUS",
      "degrees": 7.9
    },
    "snowQpf": {
      "unit": "MILLIMETERS",
      "quantity": 0
    },
    "qpf": {
      "unit": "MILLIMETERS",
      "quantity": 0.09
    }
  },
  "currentTime": "2026-06-30T18:53:16.203205608Z",
  "isDaytime": false,
  "relativeHumidity": 82,
  "uvIndex": 0,
  "thunderstormProbability": 0,
  "cloudCover": 46
}