{
  "currentTime": "2025-07-16T12:33:39.536358713Z",
  "timeZone": {
    "id": "Africa/Johannesburg"
  },
  "isDaytime": true,
  "weatherCondition": {
    "iconBaseUri": "https://maps.gstatic.com/weather/v1/sunny",
    "description": {
      "text": "Sunny",
      "languageCode": "en"
    },
    "type": "CLEAR"
  },
  "temperature": {
    "degrees": 20.3,
    "unit": "CELSIUS"
  },
  "feelsLikeTemperature": {
    "degrees": 23.7,
    "unit": "CELSIUS"
  },
  "dewPoint": {
    "degrees": 5.9,
    "unit": "CELSIUS"
  },
  "heatIndex": {
    "degrees": 23.7,
    "unit": "CELSIUS"
  },
  "windChill": {
    "degrees": 20.3,
    "unit": "CELSIUS"
  },
  "relativeHumidity": 39,
  "uvIndex": 1,
  "precipitation": {
    "probability": {
      "percent": 0,
      "type": "RAIN"
    },
    "snowQpf": {
      "quantity": 0,
      "unit": "MILLIMETERS"
    },
    "qpf": {
      "quantity": 0,
      "unit": "MILLIMETERS"
    }
  },
  "thunderstormProbability": 0,
  "airPressure": {
    "meanSeaLevelMillibars": 1016
  },
  "wind": {
    "direction": {
      "degrees": 293,
      "cardinal": "WEST_NORTHWEST"
    },
    "speed": {
      "value": 6,
      "unit": "KILOMETERS_PER_HOUR"
    },
    "gust": {
      "value": 12,
      "unit": "KILOMETERS_PER_HOUR"
    }
  },
  "visibility": {
    "distance": 16,
    "unit": "KILOMETERS"
  },
  "cloudCover": 0,
  "currentConditionsHistory": {
    "temperatureChange": {
      "degrees": 1,
      "unit": "CELSIUS"
    },
    "maxTemperature": {
      "degrees": 20.3,
      "unit": "CELSIUS"
    },
    "minTemperature": {
      "degrees": 6.9,
      "unit": "CELSIUS"
    },
    "snowQpf": {
      "quantity": 0,
      "unit": "MILLIMETERS"
    },
    "qpf": {
      "quantity": 0,
      "unit": "MILLIMETERS"
    }
  }
}