{
  "currentTime": "2026-05-05T23:42:25.246713184Z",
  "timeZone": {
    "id": "Africa/Johannesburg"
  },
  "isDaytime": false,
  "weatherCondition": {
    "iconBaseUri": "https://maps.gstatic.com/weather/v1/heavy",
    "description": {
      "text": "Heavy rain",
      "languageCode": "en"
    },
    "type": "HEAVY_RAIN"
  },
  "temperature": {
    "degrees": 17,
    "unit": "CELSIUS"
  },
  "feelsLikeTemperature": {
    "degrees": 15.7,
    "unit": "CELSIUS"
  },
  "dewPoint": {
    "degrees": 15.2,
    "unit": "CELSIUS"
  },
  "heatIndex": {
    "degrees": 17,
    "unit": "CELSIUS"
  },
  "windChill": {
    "degrees": 15.7,
    "unit": "CELSIUS"
  },
  "relativeHumidity": 89,
  "uvIndex": 0,
  "precipitation": {
    "probability": {
      "percent": 97,
      "type": "HEAVY_RAIN"
    },
    "snowQpf": {
      "quantity": 0,
      "unit": "MILLIMETERS"
    },
    "qpf": {
      "quantity": 4.04,
      "unit": "MILLIMETERS"
    }
  },
  "thunderstormProbability": 30,
  "airPressure": {
    "meanSeaLevelMillibars": 1005.86
  },
  "wind": {
    "direction": {
      "degrees": 155,
      "cardinal": "SOUTH_SOUTHEAST"
    },
    "speed": {
      "value": 32,
      "unit": "KILOMETERS_PER_HOUR"
    },
    "gust": {
      "value": 37,
      "unit": "KILOMETERS_PER_HOUR"
    }
  },
  "visibility": {
    "distance": 11,
    "unit": "KILOMETERS"
  },
  "cloudCover": 100,
  "currentConditionsHistory": {
    "temperatureChange": {
      "degrees": 0.3,
      "unit": "CELSIUS"
    },
    "maxTemperature": {
      "degrees": 16.9,
      "unit": "CELSIUS"
    },
    "minTemperature": {
      "degrees": 15.7,
      "unit": "CELSIUS"
    },
    "snowQpf": {
      "quantity": 0,
      "unit": "MILLIMETERS"
    },
    "qpf": {
      "quantity": 34.77,
      "unit": "MILLIMETERS"
    }
  }
}