{
  "currentTime": "2026-02-22T15:19:36.446418215Z",
  "timeZone": {
    "id": "Africa/Johannesburg"
  },
  "isDaytime": true,
  "weatherCondition": {
    "iconBaseUri": "https://maps.gstatic.com/weather/v1/partly_cloudy",
    "description": {
      "text": "Partly sunny",
      "languageCode": "en"
    },
    "type": "PARTLY_CLOUDY"
  },
  "temperature": {
    "degrees": 24.2,
    "unit": "CELSIUS"
  },
  "feelsLikeTemperature": {
    "degrees": 26.1,
    "unit": "CELSIUS"
  },
  "dewPoint": {
    "degrees": 20,
    "unit": "CELSIUS"
  },
  "heatIndex": {
    "degrees": 26.1,
    "unit": "CELSIUS"
  },
  "windChill": {
    "degrees": 24.2,
    "unit": "CELSIUS"
  },
  "relativeHumidity": 77,
  "uvIndex": 0,
  "precipitation": {
    "probability": {
      "percent": 0,
      "type": "NONE"
    },
    "snowQpf": {
      "quantity": 0,
      "unit": "MILLIMETERS"
    },
    "qpf": {
      "quantity": 0,
      "unit": "MILLIMETERS"
    }
  },
  "thunderstormProbability": 0,
  "airPressure": {
    "meanSeaLevelMillibars": 1006.62
  },
  "wind": {
    "direction": {
      "degrees": 86,
      "cardinal": "EAST"
    },
    "speed": {
      "value": 35,
      "unit": "KILOMETERS_PER_HOUR"
    },
    "gust": {
      "value": 42,
      "unit": "KILOMETERS_PER_HOUR"
    }
  },
  "visibility": {
    "distance": 16,
    "unit": "KILOMETERS"
  },
  "cloudCover": 54,
  "currentConditionsHistory": {
    "temperatureChange": {
      "degrees": 2.9,
      "unit": "CELSIUS"
    },
    "maxTemperature": {
      "degrees": 25.3,
      "unit": "CELSIUS"
    },
    "minTemperature": {
      "degrees": 20.6,
      "unit": "CELSIUS"
    },
    "snowQpf": {
      "quantity": 0,
      "unit": "MILLIMETERS"
    },
    "qpf": {
      "quantity": 0,
      "unit": "MILLIMETERS"
    }
  }
}