{
  "forecastDays": [
    {
      "interval": {
        "startTime": "2025-12-09T05:00:00Z",
        "endTime": "2025-12-10T05:00:00Z"
      },
      "displayDate": {
        "year": 2025,
        "month": 12,
        "day": 9
      },
      "daytimeForecast": {
        "interval": {
          "startTime": "2025-12-09T05:00:00Z",
          "endTime": "2025-12-09T17:00:00Z"
        },
        "weatherCondition": {
          "iconBaseUri": "https://maps.gstatic.com/weather/v1/drizzle",
          "description": {
            "text": "Light rain",
            "languageCode": "en"
          },
          "type": "LIGHT_RAIN"
        },
        "relativeHumidity": 67,
        "uvIndex": 10,
        "precipitation": {
          "probability": {
            "percent": 35,
            "type": "RAIN"
          },
          "snowQpf": {
            "quantity": 0,
            "unit": "MILLIMETERS"
          },
          "qpf": {
            "quantity": 0.6528,
            "unit": "MILLIMETERS"
          }
        },
        "thunderstormProbability": 10,
        "wind": {
          "direction": {
            "degrees": 223,
            "cardinal": "SOUTHWEST"
          },
          "speed": {
            "value": 29,
            "unit": "KILOMETERS_PER_HOUR"
          },
          "gust": {
            "value": 53,
            "unit": "KILOMETERS_PER_HOUR"
          }
        },
        "cloudCover": 77,
        "iceThickness": {
          "thickness": 0,
          "unit": "MILLIMETERS"
        }
      },
      "nighttimeForecast": {
        "interval": {
          "startTime": "2025-12-09T17:00:00Z",
          "endTime": "2025-12-10T05:00:00Z"
        },
        "weatherCondition": {
          "iconBaseUri": "https://maps.gstatic.com/weather/v1/drizzle",
          "description": {
            "text": "Light rain",
            "languageCode": "en"
          },
          "type": "LIGHT_RAIN"
        },
        "relativeHumidity": 82,
        "uvIndex": 0,
        "precipitation": {
          "probability": {
            "percent": 40,
            "type": "RAIN"
          },
          "snowQpf": {
            "quantity": 0,
            "unit": "MILLIMETERS"
          },
          "qpf": {
            "quantity": 2.4181,
            "unit": "MILLIMETERS"
          }
        },
        "thunderstormProbability": 10,
        "wind": {
          "direction": {
            "degrees": 147,
            "cardinal": "SOUTH_SOUTHEAST"
          },
          "speed": {
            "value": 26,
            "unit": "KILOMETERS_PER_HOUR"
          },
          "gust": {
            "value": 48,
            "unit": "KILOMETERS_PER_HOUR"
          }
        },
        "cloudCover": 100,
        "iceThickness": {
          "thickness": 0,
          "unit": "MILLIMETERS"
        }
      },
      "maxTemperature": {
        "degrees": 23.9,
        "unit": "CELSIUS"
      },
      "minTemperature": {
        "degrees": 16.5,
        "unit": "CELSIUS"
      },
      "feelsLikeMaxTemperature": {
        "degrees": 25.4,
        "unit": "CELSIUS"
      },
      "feelsLikeMinTemperature": {
        "degrees": 16,
        "unit": "CELSIUS"
      },
      "sunEvents": {
        "sunriseTime": "2025-12-09T03:02:03.039464273Z",
        "sunsetTime": "2025-12-09T17:24:27.896917184Z"
      },
      "moonEvents": {
        "moonPhase": "WANING_GIBBOUS",
        "moonriseTimes": [
          "2025-12-09T21:36:27.758828432Z"
        ],
        "moonsetTimes": [
          "2025-12-09T07:36:18.628668694Z"
        ]
      },
      "maxHeatIndex": {
        "degrees": 25.4,
        "unit": "CELSIUS"
      }
    },
    {
      "interval": {
        "startTime": "2025-12-10T05:00:00Z",
        "endTime": "2025-12-11T05:00:00Z"
      },
      "displayDate": {
        "year": 2025,
        "month": 12,
        "day": 10
      },
      "daytimeForecast": {
        "interval": {
          "startTime": "2025-12-10T05:00:00Z",
          "endTime": "2025-12-10T17:00:00Z"
        },
        "weatherCondition": {
          "iconBaseUri": "https://maps.gstatic.com/weather/v1/sunny",
          "description": {
            "text": "Sunny",
            "languageCode": "en"
          },
          "type": "CLEAR"
        },
        "relativeHumidity": 59,
        "uvIndex": 8,
        "precipitation": {
          "probability": {
            "percent": 10,
            "type": "RAIN"
          },
          "snowQpf": {
            "quantity": 0,
            "unit": "MILLIMETERS"
          },
          "qpf": {
            "quantity": 0,
            "unit": "MILLIMETERS"
          }
        },
        "thunderstormProbability": 0,
        "wind": {
          "direction": {
            "degrees": 111,
            "cardinal": "EAST_SOUTHEAST"
          },
          "speed": {
            "value": 31,
            "unit": "KILOMETERS_PER_HOUR"
          },
          "gust": {
            "value": 56,
            "unit": "KILOMETERS_PER_HOUR"
          }
        },
        "cloudCover": 87,
        "iceThickness": {
          "thickness": 0,
          "unit": "MILLIMETERS"
        }
      },
      "nighttimeForecast": {
        "interval": {
          "startTime": "2025-12-10T17:00:00Z",
          "endTime": "2025-12-11T05:00:00Z"
        },
        "weatherCondition": {
          "iconBaseUri": "https://maps.gstatic.com/weather/v1/clear",
          "description": {
            "text": "Clear",
            "languageCode": "en"
          },
          "type": "CLEAR"
        },
        "relativeHumidity": 78,
        "uvIndex": 0,
        "precipitation": {
          "probability": {
            "percent": 10,
            "type": "RAIN"
          },
          "snowQpf": {
            "quantity": 0,
            "unit": "MILLIMETERS"
          },
          "qpf": {
            "quantity": 0,
            "unit": "MILLIMETERS"
          }
        },
        "thunderstormProbability": 0,
        "wind": {
          "direction": {
            "degrees": 64,
            "cardinal": "EAST_NORTHEAST"
          },
          "speed": {
            "value": 27,
            "unit": "KILOMETERS_PER_HOUR"
          },
          "gust": {
            "value": 51,
            "unit": "KILOMETERS_PER_HOUR"
          }
        },
        "cloudCover": 100,
        "iceThickness": {
          "thickness": 0,
          "unit": "MILLIMETERS"
        }
      },
      "maxTemperature": {
        "degrees": 21.4,
        "unit": "CELSIUS"
      },
      "minTemperature": {
        "degrees": 15.1,
        "unit": "CELSIUS"
      },
      "feelsLikeMaxTemperature": {
        "degrees": 24.8,
        "unit": "CELSIUS"
      },
      "feelsLikeMinTemperature": {
        "degrees": 14,
        "unit": "CELSIUS"
      },
      "sunEvents": {
        "sunriseTime": "2025-12-10T03:02:11.177091871Z",
        "sunsetTime": "2025-12-10T17:25:13.153325905Z"
      },
      "moonEvents": {
        "moonPhase": "WANING_GIBBOUS",
        "moonsetTimes": [
          "2025-12-10T08:42:20.921493165Z"
        ]
      },
      "maxHeatIndex": {
        "degrees": 24.8,
        "unit": "CELSIUS"
      }
    },
    {
      "interval": {
        "startTime": "2025-12-11T05:00:00Z",
        "endTime": "2025-12-12T05:00:00Z"
      },
      "displayDate": {
        "year": 2025,
        "month": 12,
        "day": 11
      },
      "daytimeForecast": {
        "interval": {
          "startTime": "2025-12-11T05:00:00Z",
          "endTime": "2025-12-11T17:00:00Z"
        },
        "weatherCondition": {
          "iconBaseUri": "https://maps.gstatic.com/weather/v1/cloudy",
          "description": {
            "text": "Cloudy",
            "languageCode": "en"
          },
          "type": "CLOUDY"
        },
        "relativeHumidity": 61,
        "uvIndex": 10,
        "precipitation": {
          "probability": {
            "percent": 10,
            "type": "RAIN"
          },
          "snowQpf": {
            "quantity": 0,
            "unit": "MILLIMETERS"
          },
          "qpf": {
            "quantity": 0,
            "unit": "MILLIMETERS"
          }
        },
        "thunderstormProbability": 0,
        "wind": {
          "direction": {
            "degrees": 97,
            "cardinal": "EAST"
          },
          "speed": {
            "value": 29,
            "unit": "KILOMETERS_PER_HOUR"
          },
          "gust": {
            "value": 53,
            "unit": "KILOMETERS_PER_HOUR"
          }
        },
        "cloudCover": 100,
        "iceThickness": {
          "thickness": 0,
          "unit": "MILLIMETERS"
        }
      },
      "nighttimeForecast": {
        "interval": {
          "startTime": "2025-12-11T17:00:00Z",
          "endTime": "2025-12-12T05:00:00Z"
        },
        "weatherCondition": {
          "iconBaseUri": "https://maps.gstatic.com/weather/v1/cloudy",
          "description": {
            "text": "Cloudy",
            "languageCode": "en"
          },
          "type": "CLOUDY"
        },
        "relativeHumidity": 71,
        "uvIndex": 0,
        "precipitation": {
          "probability": {
            "percent": 10,
            "type": "RAIN"
          },
          "snowQpf": {
            "quantity": 0,
            "unit": "MILLIMETERS"
          },
          "qpf": {
            "quantity": 0,
            "unit": "MILLIMETERS"
          }
        },
        "thunderstormProbability": 0,
        "wind": {
          "direction": {
            "degrees": 252,
            "cardinal": "WEST_SOUTHWEST"
          },
          "speed": {
            "value": 37,
            "unit": "KILOMETERS_PER_HOUR"
          },
          "gust": {
            "value": 66,
            "unit": "KILOMETERS_PER_HOUR"
          }
        },
        "cloudCover": 100,
        "iceThickness": {
          "thickness": 0,
          "unit": "MILLIMETERS"
        }
      },
      "maxTemperature": {
        "degrees": 26.3,
        "unit": "CELSIUS"
      },
      "minTemperature": {
        "degrees": 17.7,
        "unit": "CELSIUS"
      },
      "feelsLikeMaxTemperature": {
        "degrees": 27.3,
        "unit": "CELSIUS"
      },
      "feelsLikeMinTemperature": {
        "degrees": 17.7,
        "unit": "CELSIUS"
      },
      "sunEvents": {
        "sunriseTime": "2025-12-11T03:02:21.218877437Z",
        "sunsetTime": "2025-12-11T17:25:57.275619984Z"
      },
      "moonEvents": {
        "moonPhase": "LAST_QUARTER",
        "moonriseTimes": [
          "2025-12-10T22:05:09.837424075Z"
        ],
        "moonsetTimes": [
          "2025-12-11T09:44:16.029078229Z"
        ]
      },
      "maxHeatIndex": {
        "degrees": 27.3,
        "unit": "CELSIUS"
      }
    },
    {
      "interval": {
        "startTime": "2025-12-12T05:00:00Z",
        "endTime": "2025-12-13T05:00:00Z"
      },
      "displayDate": {
        "year": 2025,
        "month": 12,
        "day": 12
      },
      "daytimeForecast": {
        "interval": {
          "startTime": "2025-12-12T05:00:00Z",
          "endTime": "2025-12-12T17:00:00Z"
        },
        "weatherCondition": {
          "iconBaseUri": "https://maps.gstatic.com/weather/v1/drizzle",
          "description": {
            "text": "Light rain",
            "languageCode": "en"
          },
          "type": "LIGHT_RAIN"
        },
        "relativeHumidity": 66,
        "uvIndex": 3,
        "precipitation": {
          "probability": {
            "percent": 35,
            "type": "RAIN"
          },
          "snowQpf": {
            "quantity": 0,
            "unit": "MILLIMETERS"
          },
          "qpf": {
            "quantity": 0.7925,
            "unit": "MILLIMETERS"
          }
        },
        "thunderstormProbability": 10,
        "wind": {
          "direction": {
            "degrees": 250,
            "cardinal": "WEST_SOUTHWEST"
          },
          "speed": {
            "value": 29,
            "unit": "KILOMETERS_PER_HOUR"
          },
          "gust": {
            "value": 50,
            "unit": "KILOMETERS_PER_HOUR"
          }
        },
        "cloudCover": 100,
        "iceThickness": {
          "thickness": 0,
          "unit": "MILLIMETERS"
        }
      },
      "nighttimeForecast": {
        "interval": {
          "startTime": "2025-12-12T17:00:00Z",
          "endTime": "2025-12-13T05:00:00Z"
        },
        "weatherCondition": {
          "iconBaseUri": "https://maps.gstatic.com/weather/v1/drizzle",
          "description": {
            "text": "Light rain",
            "languageCode": "en"
          },
          "type": "LIGHT_RAIN"
        },
        "relativeHumidity": 85,
        "uvIndex": 0,
        "precipitation": {
          "probability": {
            "percent": 20,
            "type": "RAIN"
          },
          "snowQpf": {
            "quantity": 0,
            "unit": "MILLIMETERS"
          },
          "qpf": {
            "quantity": 0.442,
            "unit": "MILLIMETERS"
          }
        },
        "thunderstormProbability": 10,
        "wind": {
          "direction": {
            "degrees": 252,
            "cardinal": "WEST_SOUTHWEST"
          },
          "speed": {
            "value": 26,
            "unit": "KILOMETERS_PER_HOUR"
          },
          "gust": {
            "value": 47,
            "unit": "KILOMETERS_PER_HOUR"
          }
        },
        "cloudCover": 100,
        "iceThickness": {
          "thickness": 0,
          "unit": "MILLIMETERS"
        }
      },
      "maxTemperature": {
        "degrees": 23.3,
        "unit": "CELSIUS"
      },
      "minTemperature": {
        "degrees": 16.7,
        "unit": "CELSIUS"
      },
      "feelsLikeMaxTemperature": {
        "degrees": 25.1,
        "unit": "CELSIUS"
      },
      "feelsLikeMinTemperature": {
        "degrees": 16,
        "unit": "CELSIUS"
      },
      "sunEvents": {
        "sunriseTime": "2025-12-12T03:02:33.152535874Z",
        "sunsetTime": "2025-12-12T17:26:40.217124157Z"
      },
      "moonEvents": {
        "moonPhase": "LAST_QUARTER",
        "moonriseTimes": [
          "2025-12-11T22:30:48.241665458Z"
        ],
        "moonsetTimes": [
          "2025-12-12T10:43:12.914980772Z"
        ]
      },
      "maxHeatIndex": {
        "degrees": 25.1,
        "unit": "CELSIUS"
      }
    },
    {
      "interval": {
        "startTime": "2025-12-13T05:00:00Z",
        "endTime": "2025-12-14T05:00:00Z"
      },
      "displayDate": {
        "year": 2025,
        "month": 12,
        "day": 13
      },
      "daytimeForecast": {
        "interval": {
          "startTime": "2025-12-13T05:00:00Z",
          "endTime": "2025-12-13T17:00:00Z"
        },
        "weatherCondition": {
          "iconBaseUri": "https://maps.gstatic.com/weather/v1/partly_cloudy",
          "description": {
            "text": "Partly sunny",
            "languageCode": "en"
          },
          "type": "PARTLY_CLOUDY"
        },
        "relativeHumidity": 60,
        "uvIndex": 8,
        "precipitation": {
          "probability": {
            "percent": 20,
            "type": "RAIN"
          },
          "snowQpf": {
            "quantity": 0,
            "unit": "MILLIMETERS"
          },
          "qpf": {
            "quantity": 0.2743,
            "unit": "MILLIMETERS"
          }
        },
        "thunderstormProbability": 10,
        "wind": {
          "direction": {
            "degrees": 238,
            "cardinal": "WEST_SOUTHWEST"
          },
          "speed": {
            "value": 37,
            "unit": "KILOMETERS_PER_HOUR"
          },
          "gust": {
            "value": 66,
            "unit": "KILOMETERS_PER_HOUR"
          }
        },
        "cloudCover": 96,
        "iceThickness": {
          "thickness": 0,
          "unit": "MILLIMETERS"
        }
      },
      "nighttimeForecast": {
        "interval": {
          "startTime": "2025-12-13T17:00:00Z",
          "endTime": "2025-12-14T05:00:00Z"
        },
        "weatherCondition": {
          "iconBaseUri": "https://maps.gstatic.com/weather/v1/clear",
          "description": {
            "text": "Clear",
            "languageCode": "en"
          },
          "type": "CLEAR"
        },
        "relativeHumidity": 74,
        "uvIndex": 0,
        "precipitation": {
          "probability": {
            "percent": 0,
            "type": "RAIN"
          },
          "snowQpf": {
            "quantity": 0,
            "unit": "MILLIMETERS"
          },
          "qpf": {
            "quantity": 0,
            "unit": "MILLIMETERS"
          }
        },
        "thunderstormProbability": 0,
        "wind": {
          "direction": {
            "degrees": 284,
            "cardinal": "WEST_NORTHWEST"
          },
          "speed": {
            "value": 24,
            "unit": "KILOMETERS_PER_HOUR"
          },
          "gust": {
            "value": 42,
            "unit": "KILOMETERS_PER_HOUR"
          }
        },
        "cloudCover": 27,
        "iceThickness": {
          "thickness": 0,
          "unit": "MILLIMETERS"
        }
      },
      "maxTemperature": {
        "degrees": 21.7,
        "unit": "CELSIUS"
      },
      "minTemperature": {
        "degrees": 14,
        "unit": "CELSIUS"
      },
      "feelsLikeMaxTemperature": {
        "degrees": 24.7,
        "unit": "CELSIUS"
      },
      "feelsLikeMinTemperature": {
        "degrees": 13,
        "unit": "CELSIUS"
      },
      "sunEvents": {
        "sunriseTime": "2025-12-13T03:02:46.963881259Z",
        "sunsetTime": "2025-12-13T17:27:21.931970444Z"
      },
      "moonEvents": {
        "moonPhase": "WANING_CRESCENT",
        "moonriseTimes": [
          "2025-12-12T22:55:01.543864045Z"
        ],
        "moonsetTimes": [
          "2025-12-13T11:40:31.884312387Z"
        ]
      },
      "maxHeatIndex": {
        "degrees": 24.7,
        "unit": "CELSIUS"
      }
    }
  ],
  "timeZone": {
    "id": "Africa/Johannesburg"
  }
}