{
  "forecastDays": [
    {
      "interval": {
        "startTime": "2025-08-25T05:00:00Z",
        "endTime": "2025-08-26T05:00:00Z"
      },
      "displayDate": {
        "year": 2025,
        "month": 8,
        "day": 25
      },
      "daytimeForecast": {
        "interval": {
          "startTime": "2025-08-25T05:00:00Z",
          "endTime": "2025-08-25T17:00:00Z"
        },
        "weatherCondition": {
          "iconBaseUri": "https://maps.gstatic.com/weather/v1/cloudy",
          "description": {
            "text": "Cloudy",
            "languageCode": "en"
          },
          "type": "CLOUDY"
        },
        "relativeHumidity": 66,
        "uvIndex": 2,
        "precipitation": {
          "probability": {
            "percent": 10,
            "type": "RAIN"
          },
          "snowQpf": {
            "quantity": 0,
            "unit": "MILLIMETERS"
          },
          "qpf": {
            "quantity": 0,
            "unit": "MILLIMETERS"
          }
        },
        "thunderstormProbability": 0,
        "wind": {
          "direction": {
            "degrees": 261,
            "cardinal": "WEST"
          },
          "speed": {
            "value": 29,
            "unit": "KILOMETERS_PER_HOUR"
          },
          "gust": {
            "value": 53,
            "unit": "KILOMETERS_PER_HOUR"
          }
        },
        "cloudCover": 100,
        "iceThickness": {
          "thickness": 0,
          "unit": "MILLIMETERS"
        }
      },
      "nighttimeForecast": {
        "interval": {
          "startTime": "2025-08-25T17:00:00Z",
          "endTime": "2025-08-26T05:00:00Z"
        },
        "weatherCondition": {
          "iconBaseUri": "https://maps.gstatic.com/weather/v1/mostly_clear",
          "description": {
            "text": "Clear with periodic clouds",
            "languageCode": "en"
          },
          "type": "MOSTLY_CLEAR"
        },
        "relativeHumidity": 81,
        "uvIndex": 0,
        "precipitation": {
          "probability": {
            "percent": 5,
            "type": "RAIN"
          },
          "snowQpf": {
            "quantity": 0,
            "unit": "MILLIMETERS"
          },
          "qpf": {
            "quantity": 0,
            "unit": "MILLIMETERS"
          }
        },
        "thunderstormProbability": 0,
        "wind": {
          "direction": {
            "degrees": 289,
            "cardinal": "WEST_NORTHWEST"
          },
          "speed": {
            "value": 26,
            "unit": "KILOMETERS_PER_HOUR"
          },
          "gust": {
            "value": 45,
            "unit": "KILOMETERS_PER_HOUR"
          }
        },
        "cloudCover": 55,
        "iceThickness": {
          "thickness": 0,
          "unit": "MILLIMETERS"
        }
      },
      "maxTemperature": {
        "degrees": 17.8,
        "unit": "CELSIUS"
      },
      "minTemperature": {
        "degrees": 9.7,
        "unit": "CELSIUS"
      },
      "feelsLikeMaxTemperature": {
        "degrees": 17,
        "unit": "CELSIUS"
      },
      "feelsLikeMinTemperature": {
        "degrees": 8,
        "unit": "CELSIUS"
      },
      "sunEvents": {
        "sunriseTime": "2025-08-25T04:48:07.265534629Z",
        "sunsetTime": "2025-08-25T15:57:55.819469234Z"
      },
      "moonEvents": {
        "moonPhase": "WAXING_CRESCENT",
        "moonriseTimes": [
          "2025-08-25T05:51:49.949910176Z"
        ],
        "moonsetTimes": [
          "2025-08-25T18:14:50.942494319Z"
        ]
      },
      "maxHeatIndex": {
        "degrees": 17.8,
        "unit": "CELSIUS"
      }
    },
    {
      "interval": {
        "startTime": "2025-08-26T05:00:00Z",
        "endTime": "2025-08-27T05:00:00Z"
      },
      "displayDate": {
        "year": 2025,
        "month": 8,
        "day": 26
      },
      "daytimeForecast": {
        "interval": {
          "startTime": "2025-08-26T05:00:00Z",
          "endTime": "2025-08-26T17:00:00Z"
        },
        "weatherCondition": {
          "iconBaseUri": "https://maps.gstatic.com/weather/v1/partly_cloudy",
          "description": {
            "text": "Partly sunny",
            "languageCode": "en"
          },
          "type": "PARTLY_CLOUDY"
        },
        "relativeHumidity": 70,
        "uvIndex": 5,
        "precipitation": {
          "probability": {
            "percent": 10,
            "type": "RAIN"
          },
          "snowQpf": {
            "quantity": 0,
            "unit": "MILLIMETERS"
          },
          "qpf": {
            "quantity": 0.0914,
            "unit": "MILLIMETERS"
          }
        },
        "thunderstormProbability": 0,
        "wind": {
          "direction": {
            "degrees": 90,
            "cardinal": "EAST"
          },
          "speed": {
            "value": 21,
            "unit": "KILOMETERS_PER_HOUR"
          },
          "gust": {
            "value": 39,
            "unit": "KILOMETERS_PER_HOUR"
          }
        },
        "cloudCover": 80,
        "iceThickness": {
          "thickness": 0,
          "unit": "MILLIMETERS"
        }
      },
      "nighttimeForecast": {
        "interval": {
          "startTime": "2025-08-26T17:00:00Z",
          "endTime": "2025-08-27T05:00:00Z"
        },
        "weatherCondition": {
          "iconBaseUri": "https://maps.gstatic.com/weather/v1/cloudy",
          "description": {
            "text": "Cloudy",
            "languageCode": "en"
          },
          "type": "CLOUDY"
        },
        "relativeHumidity": 84,
        "uvIndex": 0,
        "precipitation": {
          "probability": {
            "percent": 10,
            "type": "RAIN"
          },
          "snowQpf": {
            "quantity": 0,
            "unit": "MILLIMETERS"
          },
          "qpf": {
            "quantity": 0.1829,
            "unit": "MILLIMETERS"
          }
        },
        "thunderstormProbability": 0,
        "wind": {
          "direction": {
            "degrees": 9,
            "cardinal": "NORTH"
          },
          "speed": {
            "value": 18,
            "unit": "KILOMETERS_PER_HOUR"
          },
          "gust": {
            "value": 31,
            "unit": "KILOMETERS_PER_HOUR"
          }
        },
        "cloudCover": 100,
        "iceThickness": {
          "thickness": 0,
          "unit": "MILLIMETERS"
        }
      },
      "maxTemperature": {
        "degrees": 17.6,
        "unit": "CELSIUS"
      },
      "minTemperature": {
        "degrees": 9.8,
        "unit": "CELSIUS"
      },
      "feelsLikeMaxTemperature": {
        "degrees": 17.6,
        "unit": "CELSIUS"
      },
      "feelsLikeMinTemperature": {
        "degrees": 8,
        "unit": "CELSIUS"
      },
      "sunEvents": {
        "sunriseTime": "2025-08-26T04:46:52.043074453Z",
        "sunsetTime": "2025-08-26T15:58:37.533900271Z"
      },
      "moonEvents": {
        "moonPhase": "WAXING_CRESCENT",
        "moonriseTimes": [
          "2025-08-26T06:15:47.769384828Z"
        ],
        "moonsetTimes": [
          "2025-08-26T19:12:29.156893926Z"
        ]
      },
      "maxHeatIndex": {
        "degrees": 17.6,
        "unit": "CELSIUS"
      }
    },
    {
      "interval": {
        "startTime": "2025-08-27T05:00:00Z",
        "endTime": "2025-08-28T05:00:00Z"
      },
      "displayDate": {
        "year": 2025,
        "month": 8,
        "day": 27
      },
      "daytimeForecast": {
        "interval": {
          "startTime": "2025-08-27T05:00:00Z",
          "endTime": "2025-08-27T17:00:00Z"
        },
        "weatherCondition": {
          "iconBaseUri": "https://maps.gstatic.com/weather/v1/partly_cloudy",
          "description": {
            "text": "Partly sunny",
            "languageCode": "en"
          },
          "type": "PARTLY_CLOUDY"
        },
        "relativeHumidity": 72,
        "uvIndex": 3,
        "precipitation": {
          "probability": {
            "percent": 10,
            "type": "RAIN"
          },
          "snowQpf": {
            "quantity": 0,
            "unit": "MILLIMETERS"
          },
          "qpf": {
            "quantity": 0,
            "unit": "MILLIMETERS"
          }
        },
        "thunderstormProbability": 0,
        "wind": {
          "direction": {
            "degrees": 222,
            "cardinal": "SOUTHWEST"
          },
          "speed": {
            "value": 18,
            "unit": "KILOMETERS_PER_HOUR"
          },
          "gust": {
            "value": 32,
            "unit": "KILOMETERS_PER_HOUR"
          }
        },
        "cloudCover": 99,
        "iceThickness": {
          "thickness": 0,
          "unit": "MILLIMETERS"
        }
      },
      "nighttimeForecast": {
        "interval": {
          "startTime": "2025-08-27T17:00:00Z",
          "endTime": "2025-08-28T05:00:00Z"
        },
        "weatherCondition": {
          "iconBaseUri": "https://maps.gstatic.com/weather/v1/clear",
          "description": {
            "text": "Clear",
            "languageCode": "en"
          },
          "type": "CLEAR"
        },
        "relativeHumidity": 89,
        "uvIndex": 0,
        "precipitation": {
          "probability": {
            "percent": 0,
            "type": "RAIN"
          },
          "snowQpf": {
            "quantity": 0,
            "unit": "MILLIMETERS"
          },
          "qpf": {
            "quantity": 0,
            "unit": "MILLIMETERS"
          }
        },
        "thunderstormProbability": 0,
        "wind": {
          "direction": {
            "degrees": 312,
            "cardinal": "NORTHWEST"
          },
          "speed": {
            "value": 10,
            "unit": "KILOMETERS_PER_HOUR"
          },
          "gust": {
            "value": 16,
            "unit": "KILOMETERS_PER_HOUR"
          }
        },
        "cloudCover": 20,
        "iceThickness": {
          "thickness": 0,
          "unit": "MILLIMETERS"
        }
      },
      "maxTemperature": {
        "degrees": 19.6,
        "unit": "CELSIUS"
      },
      "minTemperature": {
        "degrees": 11.3,
        "unit": "CELSIUS"
      },
      "feelsLikeMaxTemperature": {
        "degrees": 24.9,
        "unit": "CELSIUS"
      },
      "feelsLikeMinTemperature": {
        "degrees": 10,
        "unit": "CELSIUS"
      },
      "sunEvents": {
        "sunriseTime": "2025-08-27T04:45:36.122739900Z",
        "sunsetTime": "2025-08-27T15:59:19.173271770Z"
      },
      "moonEvents": {
        "moonPhase": "WAXING_CRESCENT",
        "moonriseTimes": [
          "2025-08-27T06:40:10.509342632Z"
        ],
        "moonsetTimes": [
          "2025-08-27T20:10:03.070938298Z"
        ]
      },
      "maxHeatIndex": {
        "degrees": 24.9,
        "unit": "CELSIUS"
      }
    },
    {
      "interval": {
        "startTime": "2025-08-28T05:00:00Z",
        "endTime": "2025-08-29T05:00:00Z"
      },
      "displayDate": {
        "year": 2025,
        "month": 8,
        "day": 28
      },
      "daytimeForecast": {
        "interval": {
          "startTime": "2025-08-28T05:00:00Z",
          "endTime": "2025-08-28T17:00:00Z"
        },
        "weatherCondition": {
          "iconBaseUri": "https://maps.gstatic.com/weather/v1/cloudy",
          "description": {
            "text": "Cloudy",
            "languageCode": "en"
          },
          "type": "CLOUDY"
        },
        "relativeHumidity": 75,
        "uvIndex": 4,
        "precipitation": {
          "probability": {
            "percent": 10,
            "type": "RAIN"
          },
          "snowQpf": {
            "quantity": 0,
            "unit": "MILLIMETERS"
          },
          "qpf": {
            "quantity": 0,
            "unit": "MILLIMETERS"
          }
        },
        "thunderstormProbability": 0,
        "wind": {
          "direction": {
            "degrees": 125,
            "cardinal": "SOUTHEAST"
          },
          "speed": {
            "value": 13,
            "unit": "KILOMETERS_PER_HOUR"
          },
          "gust": {
            "value": 24,
            "unit": "KILOMETERS_PER_HOUR"
          }
        },
        "cloudCover": 100,
        "iceThickness": {
          "thickness": 0,
          "unit": "MILLIMETERS"
        }
      },
      "nighttimeForecast": {
        "interval": {
          "startTime": "2025-08-28T17:00:00Z",
          "endTime": "2025-08-29T05:00:00Z"
        },
        "weatherCondition": {
          "iconBaseUri": "https://maps.gstatic.com/weather/v1/cloudy",
          "description": {
            "text": "Cloudy",
            "languageCode": "en"
          },
          "type": "CLOUDY"
        },
        "relativeHumidity": 89,
        "uvIndex": 0,
        "precipitation": {
          "probability": {
            "percent": 10,
            "type": "RAIN"
          },
          "snowQpf": {
            "quantity": 0,
            "unit": "MILLIMETERS"
          },
          "qpf": {
            "quantity": 0,
            "unit": "MILLIMETERS"
          }
        },
        "thunderstormProbability": 0,
        "wind": {
          "direction": {
            "degrees": 277,
            "cardinal": "WEST"
          },
          "speed": {
            "value": 6,
            "unit": "KILOMETERS_PER_HOUR"
          },
          "gust": {
            "value": 11,
            "unit": "KILOMETERS_PER_HOUR"
          }
        },
        "cloudCover": 100,
        "iceThickness": {
          "thickness": 0,
          "unit": "MILLIMETERS"
        }
      },
      "maxTemperature": {
        "degrees": 19.8,
        "unit": "CELSIUS"
      },
      "minTemperature": {
        "degrees": 11.4,
        "unit": "CELSIUS"
      },
      "feelsLikeMaxTemperature": {
        "degrees": 24.9,
        "unit": "CELSIUS"
      },
      "feelsLikeMinTemperature": {
        "degrees": 10,
        "unit": "CELSIUS"
      },
      "sunEvents": {
        "sunriseTime": "2025-08-28T04:44:19.531752637Z",
        "sunsetTime": "2025-08-28T16:00:00.740658510Z"
      },
      "moonEvents": {
        "moonPhase": "WAXING_CRESCENT",
        "moonriseTimes": [
          "2025-08-28T07:06:10.473934842Z"
        ],
        "moonsetTimes": [
          "2025-08-28T21:08:14.988682463Z"
        ]
      },
      "maxHeatIndex": {
        "degrees": 24.9,
        "unit": "CELSIUS"
      }
    },
    {
      "interval": {
        "startTime": "2025-08-29T05:00:00Z",
        "endTime": "2025-08-30T05:00:00Z"
      },
      "displayDate": {
        "year": 2025,
        "month": 8,
        "day": 29
      },
      "daytimeForecast": {
        "interval": {
          "startTime": "2025-08-29T05:00:00Z",
          "endTime": "2025-08-29T17:00:00Z"
        },
        "weatherCondition": {
          "iconBaseUri": "https://maps.gstatic.com/weather/v1/mostly_cloudy",
          "description": {
            "text": "Mostly cloudy",
            "languageCode": "en"
          },
          "type": "MOSTLY_CLOUDY"
        },
        "relativeHumidity": 77,
        "uvIndex": 3,
        "precipitation": {
          "probability": {
            "percent": 10,
            "type": "RAIN"
          },
          "snowQpf": {
            "quantity": 0,
            "unit": "MILLIMETERS"
          },
          "qpf": {
            "quantity": 0,
            "unit": "MILLIMETERS"
          }
        },
        "thunderstormProbability": 0,
        "wind": {
          "direction": {
            "degrees": 250,
            "cardinal": "WEST_SOUTHWEST"
          },
          "speed": {
            "value": 18,
            "unit": "KILOMETERS_PER_HOUR"
          },
          "gust": {
            "value": 32,
            "unit": "KILOMETERS_PER_HOUR"
          }
        },
        "cloudCover": 88,
        "iceThickness": {
          "thickness": 0,
          "unit": "MILLIMETERS"
        }
      },
      "nighttimeForecast": {
        "interval": {
          "startTime": "2025-08-29T17:00:00Z",
          "endTime": "2025-08-30T05:00:00Z"
        },
        "weatherCondition": {
          "iconBaseUri": "https://maps.gstatic.com/weather/v1/mostly_cloudy_night",
          "description": {
            "text": "Mostly cloudy",
            "languageCode": "en"
          },
          "type": "MOSTLY_CLOUDY"
        },
        "relativeHumidity": 85,
        "uvIndex": 0,
        "precipitation": {
          "probability": {
            "percent": 25,
            "type": "RAIN"
          },
          "snowQpf": {
            "quantity": 0,
            "unit": "MILLIMETERS"
          },
          "qpf": {
            "quantity": 0.1524,
            "unit": "MILLIMETERS"
          }
        },
        "thunderstormProbability": 10,
        "wind": {
          "direction": {
            "degrees": 263,
            "cardinal": "WEST"
          },
          "speed": {
            "value": 31,
            "unit": "KILOMETERS_PER_HOUR"
          },
          "gust": {
            "value": 56,
            "unit": "KILOMETERS_PER_HOUR"
          }
        },
        "cloudCover": 90,
        "iceThickness": {
          "thickness": 0,
          "unit": "MILLIMETERS"
        }
      },
      "maxTemperature": {
        "degrees": 20.6,
        "unit": "CELSIUS"
      },
      "minTemperature": {
        "degrees": 14.9,
        "unit": "CELSIUS"
      },
      "feelsLikeMaxTemperature": {
        "degrees": 24.8,
        "unit": "CELSIUS"
      },
      "feelsLikeMinTemperature": {
        "degrees": 14,
        "unit": "CELSIUS"
      },
      "sunEvents": {
        "sunriseTime": "2025-08-29T04:43:02.297344948Z",
        "sunsetTime": "2025-08-29T16:00:42.239762189Z"
      },
      "moonEvents": {
        "moonPhase": "WAXING_CRESCENT",
        "moonriseTimes": [
          "2025-08-29T07:35:07.079835301Z"
        ]
      },
      "maxHeatIndex": {
        "degrees": 24.8,
        "unit": "CELSIUS"
      }
    }
  ],
  "timeZone": {
    "id": "Africa/Johannesburg"
  }
}